claude_llm_tools/__init__.py
claude_llm_tools/errors.py
claude_llm_tools/jsonschema.py
claude_llm_tools/main.py
claude_llm_tools/models.py
claude_llm_tools/state.py
claude_llm_tools/py.typed
claude_llm_tools-0.3.0.dist-info/METADATA
claude_llm_tools-0.3.0.dist-info/WHEEL
claude_llm_tools-0.3.0.dist-info/licenses/LICENSE
claude_llm_tools-0.3.0.dist-info/RECORD
