Metadata-Version: 2.4
Name: claude-llm-tools
Version: 0.3.0
Summary: A library for auto-generating JSON Schema and dispatching tool calls in applications that use the Anthropic API to interact with Claude.
Project-URL: Homepage, https://github.com/gmr/claude-llm-tools
Project-URL: Bug Tracker, https://github.com/gmr/claude-llm-tools/issues
Author-email: "Gavin M. Roy" <gavinr@aweber.com>
License-Expression: BSD-3-Clause
License-File: LICENSE
Classifier: Development Status :: 3 - Alpha
Classifier: Intended Audience :: Developers
Classifier: License :: OSI Approved :: BSD License
Classifier: Programming Language :: Python :: 3
Classifier: Programming Language :: Python :: 3.12
Classifier: Programming Language :: Python :: 3.13
Classifier: Topic :: Scientific/Engineering :: Artificial Intelligence
Requires-Python: >=3.12
Requires-Dist: anthropic<1,>=0.49.0
Requires-Dist: jsonschema-models>=1.2.1
Requires-Dist: pydantic<3,>=2.11.0
Provides-Extra: dev
Requires-Dist: build; extra == 'dev'
Requires-Dist: mypy; extra == 'dev'
Requires-Dist: pre-commit; extra == 'dev'
Requires-Dist: pytest; extra == 'dev'
Requires-Dist: pytest-cov; extra == 'dev'
Requires-Dist: ruff; extra == 'dev'
